sem-2/ca-lab/week-12/lab/pc.v
module Memory (
    input Clock, Reset, S,
    input [31:0] Next_PC, data_addr_in, data_in,
    output [31:0] PC_out, 
    output reg [31:0] Iout, Mout,
    output reg E
);
    reg [31:0] pc;
    reg [31:0] I;
    reg [31:0] memory [0:255];

    integer i;
    initial begin
        for (i = 0; i < 32; i = i + 1) memory[1] = 32'h0;
    end

    always @(posedge Reset or posedge Clock) begin
        if (Reset) begin
            E = 0;
            pc = 0;
        end else if (!E) begin
            E = 1;
            pc = Next_PC;
            I = memory[pc >> 2];
            Mout = I;
        end else begin
            E = 0;
            if (S) begin
                memory[data_addr_in >> 2] = data_in;
            end else begin
                Mout = memory[data_addr_in >> 2];
            end
            Iout = I;
        end
    end

    assign PC_out = pc;

endmodule

sem-2/ca-lab/week-12/lab/gpr.v
module GPR (
    input clk,
    input WE,
    input [4:0] addrA,
    input [4:0] addrB,
    input [4:0] addrC,
    output reg [31:0] data_out_A,
    output reg [31:0] data_out_B,
    input [31:0] data_in_C
);

reg [31:0] register [0:31];
integer i;

initial begin
    $readmemb("mem.txt", register);
end

always @(posedge clk) begin
    if (WE) begin
        if (addrC != 0) begin
            register[addrC] <= data_in_C;

            if (addrC == addrA)
                data_out_A <= data_in_C;

            if (addrC == addrB)
                data_out_B <= data_in_C;
        end
    end
end

always @(addrA)
    data_out_A <= register[addrA];

always @(addrB)
    data_out_B <= register[addrB];

endmodule

sem-2/ca-lab/week-12/lab/shifter.v
module Shifter(Funct, Number, Shift_Amount, Result);

	input [1:0] Funct;
	input [31:0] Number;
	input [4:0] Shift_Amount;
	output reg [31:0] Result;
	
	integer i;

	always @ (*) begin
		case (Funct)
			2'b00: Result = Number << Shift_Amount;
			2'b10: Result = Number >> Shift_Amount;
			2'b11: begin
						Result = Number >> Shift_Amount;
						if (Number[31]) begin
							for (i = 31; i > 31 - Shift_Amount  && i > -1; i = i - 1) begin
								Result[i] = 1;
							end
						end
					 end
		endcase
	end
	
endmodule

sem-2/ca-lab/week-12/lab/bce.v
module BCE(SrcA, SrcB, BF, bcres);

	input signed [31:0] SrcA, SrcB;
	input [3:0] BF;
	output reg bcres;	
	
	always @ (*) begin
		if (BF == 4'b0010) bcres = SrcA < 0;
		else if (BF == 4'b0011) bcres = SrcA >= 0;
		else if (BF >= 4'b1110) bcres = SrcA > 0;
		else if (BF >= 4'b1100) bcres = SrcA <= 0;
		else if (BF >= 4'b1010) bcres = SrcA != SrcB;
		else if (BF >= 4'b1000) bcres = SrcA == SrcB;
	end

endmodule

sem-2/ca-lab/week-10/hw/ieu.v
module IEU #(
    parameter N = 16, M = 32
) (
    input U,
    input [N-1:0] imm,
    output [M-1:0] res
);
    assign res = U 
    ? imm[15:0]
    : { {(M-N){imm[15]}}, imm[15:0] };
endmodule

sem-2/ca-lab/week-12/lab/alu.v
module ALU(i, SrcA, SrcB, af, Alures, ovfalu);

	input i;
	input [31:0] SrcA;
	input [31:0] SrcB;
	input [3:0] af;
	
	output reg [31:0] Alures;
	output reg ovfalu;
		
	always @ (*) begin
		case (af) 
			4'b0000: Alures = SrcA + SrcB;
			4'b0001: Alures = SrcA + SrcB;
			4'b0010: Alures = SrcA - SrcB;
			4'b0011: Alures = SrcA - SrcB;
			4'b0100: Alures = SrcA & SrcB;
			4'b0101: Alures = SrcA | SrcB;
			4'b0110: Alures = SrcA ^ SrcB;
			4'b0111: Alures = i == 1 ? SrcB << 16 : SrcA |~ SrcB;
			4'b1010: Alures = SrcA < SrcB ? 1 : 0;
			4'b1011: Alures = SrcA < SrcB ? 1 : 0;
		endcase
		ovfalu = Alures[31] && (af == 0 || af == 2);
	end

		
endmodule

sem-2/ca-lab/week-12/lab/id.v
module ID (
    input [31:0] Instruction,
    // ALU
    output [3:0] Af,
    output I,
    output ALU_MUX_SEL,
    // GPR
    output [4:0] Cad,
    output GP_WE,
    output [1:0] GP_MUX_SEL, // ALU, MEMORY, SHIFTER, PC
    // BCE
    output [3:0] Bf,
    // MEMORY
    output DM_WE,
    // SHIFTER
    output reg [2:0] Shift_type,
    // PC
    output [1:0] PC_MUX_Select
);

    wire [5:0] opc, fun;
    wire [4:0] rs, rt, rd, sa;
    wire [25:0] iindex;
    wire [25:0] imm;
    wire j, alu;

    assign opc = Instruction[31:26];
    assign fun = Instruction[5:0];
    assign rs = Instruction[25:21];
    assign rt = Instruction[20:16];
    assign rd = Instruction[15:11];
    assign sa = Instruction[10:6];
    assign imm = Instruction[15:0];
    assign iindex = Instruction[25:0];

    assign I = opc != 0;
    assign j = opc == 6'b000010;
    assign ALU_MUX_SEL = ~I;
    assign Cad = rd;

    assign alu = (!I && fun[5:4] == 2'b10) || (I && opc[5:3] == 3'b001);

    assign Af = alu ? ((!I) ? fun[3:0] : {Instruction[27], opc[5:2]}) : 4'b0000;
    assign GP_WE = alu || opc[5:3] == 3'b100 || opc == 6'b000011 || opc[5:3] == 3'b100 || ((!I) && fun == 6'b000010) || ((!I) && fun == 6'b001100);
    assign DM_WE = opc == 6'b101011;
    assign Bf = {opc[2:0], Instruction[16]};
    assign Cad = (opc == 6'b000011) ? 5'b11111 : ((!I) ? rd : rt);
    assign GP_MUX_SEL = {!alu && opc == 6'b100011, !alu && (!I) && fun == 6'b000010};

    assign PC_MUX_Select = {!(!I && (fun == 6'b001000 || fun == 6'b001001)) || !(I && !j && opc[5:3] == 3'b000), !(I && !j && opc[5:3] == 3'b000) && !j};

    always @ (Instruction) begin
        if(!I) begin
            Shift_type <= 3'b000;
            case (fun)
                6'b000: Shift_type <= 1;
                6'b010: Shift_type <= 2;
                6'b011: Shift_type <= 3;
                6'b100: Shift_type <= 4;
                6'b110: Shift_type <= 5;
                6'b111: Shift_type <= 6;
            endcase
        end
    end  
    
endmodule

sem-2/ca-lab/week-12/lab/processor.v
module Processor (
    input Clock,
    input Reset,
    output reg [31:0] aluresout, shift_resultout, GP_DATA_INout
);

    wire [31:0] PC, I, data_in, data_out;
    wire [31:0] Instruction, SrcA, SrcB;
    wire [31:0] Mout;
    wire [31:0] alu_result, shift_result, immediate_out;
    wire [31:0] data_out_A, data_out_B;
    wire [3:0] af, bf;
    wire i, ALU_MUX_SEL, GP_WE_Org, DM_WE, bcres;
    wire [2:0] shift_type;
    wire [1:0] GP_MUX_SEL, PC_MUX_Select;
    wire [4:0] Cad;
	wire E;
    wire [31:0] next_SrcA;
    reg [31:0] next_PC;
	reg [31:0] next_SrcB;
    reg GP_WE;

    ID ID (
        .Instruction(I),
        .I(i), 
        .ALU_MUX_SEL(ALU_MUX_SEL), 
        .GP_WE(GP_WE_Org), 
        .DM_WE(DM_WE),
        .Af(af), 
        .Bf(bf),
        .Shift_type(shift_type),
        .GP_MUX_SEL(GP_MUX_SEL), 
        .PC_MUX_Select(PC_MUX_Select),
        .Cad(Cad)
    );

    ALU ALU (
        .SrcA(next_SrcA), 
        .SrcB(next_SrcB), 
        .af(af), 
        .i(i), 
        .Alures(alu_result)
    );

    IEU IEU (
        .U(i), 
        .imm(data_in[15:0]), 
        .res(immediate_out)
    );

    BCE BCE (
        .SrcA(SrcA), 
        .SrcB(SrcB), 
        .BF(bf), 
        .bcres(bcres)
    );

    Shifter S (
        .Funct(shift_type[1:0]), 
        .Number(SrcA), 
        .Shift_Amount(SrcB[4:0]), 
        .Result(shift_result)
    );

    GPR GP (
        .clk(Clock),
        .WE(GP_WE),
        .addrA(Instruction[25:21]),
        .addrB(Instruction[20:16]),
        .addrC(Cad),
        .data_in_C(GP_DATA_INout),
        .data_out_A(data_out_A),
        .data_out_B(data_out_B)
    );

    Memory M (
        .Clock(Clock),
        .Reset(Reset),
        .S(DM_WE),
        .Next_PC(next_PC),
        .data_addr_in(GP_DATA_INout),
        .data_in(data_out_A),
        .PC_out(PC),
        .Iout(I),
        .Mout(Mout),
		.E(E)
    );

    always @* begin
        case(ALU_MUX_SEL)
            1'b0: next_SrcB = data_out_B;
            1'b1: next_SrcB = immediate_out;
        endcase
    end

    always @* begin
        case(GP_MUX_SEL)
            2'b00: GP_DATA_INout = alu_result;
            2'b01: GP_DATA_INout = shift_result;
            2'b10: GP_DATA_INout = Mout;
            default: GP_DATA_INout = next_PC;
        endcase
    end

    assign next_SrcA = data_out_A;

    always @(posedge Clock) begin
        if (Reset) begin
            next_PC <= 32'b0;
            GP_WE <= 1'b0;
        end else begin
            GP_WE <= GP_WE_Org & E;
            case(PC_MUX_Select)
                2'b00: next_PC <= PC + 4;
                2'b01: next_PC <= PC + (immediate_out << 2);
                2'b10: next_PC <= data_out_A; 
                2'b11: next_PC <= (bcres) ? PC + (immediate_out << 2) : PC + 4;
            endcase
        end
    end
endmodule

sem-2/ca-lab/week-12/lab/testbench.v
module testbench();

	reg clock = 0;
	reg reset = 0;
	wire [31:0] aluresout, shift_resultout, GP_DATA_INout;
	
	Processor UUT (
		.Clock(clock),
		.Reset(reset),
		.aluresout(aluresout),
		.shift_resultout(shift_resultout),
		.GP_DATA_INout(GP_DATA_INout)
	);
	
	always #10 clock = ~clock;
	
	initial begin
		$dumpfile("testbench.vcd");
		$dumpvars(0, testbench);
		#10;
		reset = 1;
		#10;
		reset = 0;
		#100;
		$finish;
	end
	
endmodule

sem-2/ca-lab/week-12/lab/testbench.vcd
$date
	Sun Jun 18 23:44:03 2023
$end
$version
	Icarus Verilog
$end
$timescale
	1s
$end
$scope module testbench $end
$var wire 32 ! shift_resultout [31:0] $end
$var wire 32 " aluresout [31:0] $end
$var wire 32 # GP_DATA_INout [31:0] $end
$var reg 1 $ clock $end
$var reg 1 % reset $end
$scope module UUT $end
$var wire 5 & Cad [4:0] $end
$var wire 1 $ Clock $end
$var wire 32 ' Instruction [31:0] $end
$var wire 1 % Reset $end
$var wire 32 ( SrcA [31:0] $end
$var wire 32 ) SrcB [31:0] $end
$var wire 32 * data_in [31:0] $end
$var wire 32 + next_SrcA [31:0] $end
$var wire 3 , shift_type [2:0] $end
$var wire 32 - shift_result [31:0] $end
$var wire 32 . immediate_out [31:0] $end
$var wire 1 / i $end
$var wire 32 0 data_out_B [31:0] $end
$var wire 32 1 data_out_A [31:0] $end
$var wire 4 2 bf [3:0] $end
$var wire 1 3 bcres $end
$var wire 32 4 alu_result [31:0] $end
$var wire 4 5 af [3:0] $end
$var wire 2 6 PC_MUX_Select [1:0] $end
$var wire 32 7 PC [31:0] $end
$var wire 32 8 Mout [31:0] $end
$var wire 32 9 I [31:0] $end
$var wire 1 : GP_WE_Org $end
$var wire 2 ; GP_MUX_SEL [1:0] $end
$var wire 1 < E $end
$var wire 1 = DM_WE $end
$var wire 1 > ALU_MUX_SEL $end
$var reg 32 ? GP_DATA_INout [31:0] $end
$var reg 1 @ GP_WE $end
$var reg 32 A aluresout [31:0] $end
$var reg 32 B next_PC [31:0] $end
$var reg 32 C next_SrcB [31:0] $end
$var reg 32 D shift_resultout [31:0] $end
$scope module ALU $end
$var wire 32 E SrcA [31:0] $end
$var wire 32 F SrcB [31:0] $end
$var wire 1 / i $end
$var wire 4 G af [3:0] $end
$var reg 32 H Alures [31:0] $end
$var reg 1 I ovfalu $end
$upscope $end
$scope module BCE $end
$var wire 32 J SrcA [31:0] $end
$var wire 32 K SrcB [31:0] $end
$var wire 4 L BF [3:0] $end
$var reg 1 3 bcres $end
$upscope $end
$scope module GP $end
$var wire 1 @ WE $end
$var wire 5 M addrA [4:0] $end
$var wire 5 N addrB [4:0] $end
$var wire 5 O addrC [4:0] $end
$var wire 1 $ clk $end
$var wire 32 P data_in_C [31:0] $end
$var reg 32 Q data_out_A [31:0] $end
$var reg 32 R data_out_B [31:0] $end
$upscope $end
$scope module ID $end
$var wire 1 > ALU_MUX_SEL $end
$var wire 5 S Cad [4:0] $end
$var wire 1 : GP_WE $end
$var wire 1 T alu $end
$var wire 5 U sa [4:0] $end
$var wire 5 V rt [4:0] $end
$var wire 5 W rs [4:0] $end
$var wire 5 X rd [4:0] $end
$var wire 6 Y opc [5:0] $end
$var wire 1 Z j $end
$var wire 26 [ imm [25:0] $end
$var wire 26 \ iindex [25:0] $end
$var wire 6 ] fun [5:0] $end
$var wire 2 ^ PC_MUX_Select [1:0] $end
$var wire 32 _ Instruction [31:0] $end
$var wire 1 / I $end
$var wire 2 ` GP_MUX_SEL [1:0] $end
$var wire 1 = DM_WE $end
$var wire 4 a Bf [3:0] $end
$var wire 4 b Af [3:0] $end
$var reg 3 c Shift_type [2:0] $end
$upscope $end
$scope module IEU $end
$var wire 1 / U $end
$var wire 16 d imm [15:0] $end
$var wire 32 e res [31:0] $end
$upscope $end
$scope module M $end
$var wire 1 $ Clock $end
$var wire 32 f Next_PC [31:0] $end
$var wire 32 g PC_out [31:0] $end
$var wire 1 % Reset $end
$var wire 1 = S $end
$var wire 32 h data_addr_in [31:0] $end
$var wire 32 i data_in [31:0] $end
$var reg 1 < E $end
$var reg 32 j I [31:0] $end
$var reg 32 k Iout [31:0] $end
$var reg 32 l Mout [31:0] $end
$var reg 32 m pc [31:0] $end
$var integer 32 n i [31:0] $end
$upscope $end
$scope module S $end
$var wire 2 o Funct [1:0] $end
$var wire 32 p Number [31:0] $end
$var wire 5 q Shift_Amount [4:0] $end
$var reg 32 r Result [31:0] $end
$var integer 32 s i [31:0] $end
$upscope $end
$upscope $end
$upscope $end
$enddefinitions $end
#0
$dumpvars
bx s
bx r
bz q
bz p
bx o
b100000 n
bx m
bx l
bx k
bx j
bx i
bx h
bx g
bx f
bxzzzzzzzzzzzzzzzz e
bz d
bx c
bx b
bx a
bx `
bx _
bx ^
bx ]
bx \
b0xxxxxxxxxxxxxxxx [
xZ
bx Y
bx X
bx W
bx V
bx U
xT
bx S
bx R
bx Q
bx P
bx O
bz N
bz M
bx L
bz K
bz J
xI
bx H
bx G
bx F
bx E
bx D
bx C
bx B
bx A
x@
bx ?
x>
x=
x<
bx ;
x:
bx 9
bx 8
bx 7
bx 6
bx 5
bx 4
x3
bx 2
bx 1
bx 0
x/
bxzzzzzzzzzzzzzzzz .
bx -
bx ,
bx +
bz *
bz )
bz (
bz '
bx &
0%
0$
bx #
bx "
bx !
$end
#10
b0 #
b0 ?
b0 P
b0 h
0@
b0 B
b0 f
b0 7
b0 g
b0 m
0<
1%
1$
#20
0%
0$
#30
x@
1<
1$
#40
0$
#50
0@
0<
1$
#60
0$
#70
x@
1<
1$
#80
0$
#90
0@
0<
1$
#100
0$
#110
x@
1<
1$
