sem-2/ca-lab/week-11/hw/id.v
module InstructionDecoder (
    input [31:0] Instruction,
    // ALU
    output [3:0] Af,
    output I,
    output ALU_MUX_SEL,
    // GPR
    output [4:0] Cad,
    output GP_WE,
    output [1:0] GP_MUX_SEL, // ALU, MEMORY, SHIFTER, PC
    // BCE
    output [3:0] Bf,
    // MEMORY
    output DM_WE,
    // SHIFTER
    output reg [2:0] Shift_type,
    // PC
    output [1:0] PC_MUX_Select
);

    wire [5:0] opc, fun;
    wire [4:0] rs, rt, rd, sa;
    wire [25:0] iindex;
    wire [25:0] imm;
    wire j, alu;

    assign opc = Instruction[31:26];
    assign fun = Instruction[5:0];
    assign rs = Instruction[25:21];
    assign rt = Instruction[20:16];
    assign rd = Instruction[15:11];
    assign sa = Instruction[10:6];
    assign imm = Instruction[15:0];
    assign iindex = Instruction[25:0];

    assign I = opc != 0;
    assign j = opc == 6'b000010;
    assign ALU_MUX_SEL = ~I;
    assign Cad = rd;

    assign alu = (!I && fun[5:4] == 2'b10) || (I && opc[5:3] == 3'b001);

    assign Af = alu ? ((!I) ? fun[3:0] : {Instruction[27], opc[5:2]}) : 4'b0000;
    assign GP_WE = alu || opc[5:3] == 3'b100 || opc == 6'b000011 || opc[5:3] == 3'b100 || ((!I) && fun == 6'b000010) || ((!I) && fun == 6'b001100);
    assign DM_WE = opc == 6'b101011;
    assign Bf = {opc[2:0], Instruction[16]};
    assign Cad = (opc == 6'b000011) ? 5'b11111 : ((!I) ? rd : rt);
    assign GP_MUX_SEL = {!alu && opc == 6'b100011, !alu && (!I) && fun == 6'b000010};

    assign PC_MUX_Select = {!(!I && (fun == 6'b001000 || fun == 6'b001001)) || !(I && !j && opc[5:3] == 3'b000), !(I && !j && opc[5:3] == 3'b000) && !j};

    always @ (Instruction) begin
        if(!I) begin
            Shift_type <= 3'b000;
            case (fun)
                6'b000: Shift_type <= 1;
                6'b010: Shift_type <= 2;
                6'b011: Shift_type <= 3;
                6'b100: Shift_type <= 4;
                6'b110: Shift_type <= 5;
                6'b111: Shift_type <= 6;
            endcase
        end
    end  
    
endmodule

sem-2/ca-lab/week-11/lab/id-tb.v
module id_tb();
    reg [31:0] instruction;
    wire [3:0] Af;
    wire I;
    wire ALU_MUX_SEL;
    wire [4:0] Cad;
    wire GP_WE;
    wire [1:0] GP_MUX_SEL;
    wire [3:0] Bf;
    wire DM_WE;
    wire [2:0] Shift_type;
    wire [1:0] PC_MUX_Select;


    InstructionDecoder UUT (
        .Instruction(instruction),
        .Af(Af),
        .I(I),
        .ALU_MUX_SEL(ALU_MUX_SEL),
        .Cad(Cad),
        .GP_WE(GP_WE),
        .GP_MUX_SEL(GP_MUX_SEL),
        .Bf(Bf),
        .DM_WE(DM_WE),
        .Shift_type(Shift_type),
        .PC_MUX_Select(PC_MUX_Select)
    );

    initial begin
		$dumpfile("id-tb.vcd"); 
		$dumpvars(0, id_tb);
        /////////////////// TEST ITYPE INSTRUCTIONS
        instruction = 32'b10001100100001010000000000000100; // LW
        #10;
        instruction = 32'b10101100100001010000000000000100; // SW
        #10;
        instruction = 32'b00100000100001010000000000000100; // ADDI
        #10;
        instruction = 32'b00100100100001010000000000000100; // ADDIU
        #10;
        instruction = 32'b00101000100001010000000000000100; // SUBI
        #10;
        instruction = 32'b00101100100001010000000000000100; // SUBIU
        #10;
        instruction = 32'b00110000100001010000000000000100; // ANDI
        #10;
        instruction = 32'b00110100100001010000000000000100; // ORI
        #10;
        instruction = 32'b00111000100001010000000000000100; // XORI
        #10;
        instruction = 32'b00111100100001010000000000000100; // LUI
        #10;
        //////BRANCH
        instruction = 32'b00000100100000000000000000000100; // bltz
        #10;
        instruction = 32'b00000100100000010000000000000100; // bGEz
        #10;
        instruction = 32'b00010000100000010000000000000100; // beq
        #10;
        instruction = 32'b00010100100000010000000000000100; // bne
        #10;
        instruction = 32'b00011000100000000000000000000100; // blez
        #10;
        instruction = 32'b00011100100000000000000000000100; // bgtz
        #10;
        ////////////////// TEST RTYPE
        instruction = 32'b00000000100001010010000001000000; // SLL
        #10;
        instruction = 32'b00000000100001010010000001000010; // SRL
        #10;
        instruction = 32'b00000000100001010010000001000011; // SRA
        #10;
        instruction = 32'b00000000100001010010000000000100; // SLLV
        #10;
        instruction = 32'b00000000100001010010000000000110; // SRLV
        #10;
        instruction = 32'b00000000100001010010000000000111; // SRAV
        #10;
        instruction = 32'b00000000100001010010000000100000; // ADD
        #10;
        instruction = 32'b00000000100001010010000000100001; // ADDU
        #10;
        instruction = 32'b00000000100001010010000000100010; // SUB
        #10;
        instruction = 32'b00000000100001010010000000100011; // SUBU
        #10;
        instruction = 32'b00000000100001010010000000100100; // AND
        #10;
        instruction = 32'b00000000100001010010000000100101; // OR
        #10;
        instruction = 32'b00000000100001010010000000100110; // XOR
        #10;
        instruction= 32'b00000000100001010010000000100111; // NOR
        #10;
        instruction = 32'b00000000100001010010000000101010; // SLT
        #10;
        instruction = 32'b00000000100001010010000000101011; // SLTU
        #10;
        instruction = 32'b00000000100001010010000000001000; // JR
        #10;
        instruction = 32'b00000000100001010010000000001001; // JALR
        #10;
        /////////////// JTYPE
        instruction = 32'b00001000000000000000000000001001; // J
        #10;
        instruction = 32'b00001100000000000000000000001001; // JAL
        #10;
		$finish;
    end
endmodule

sem-2/ca-lab/week-11/hw/id-tb.vcd
$date
	Sat Jun 17 23:35:42 2023
$end
$version
	Icarus Verilog
$end
$timescale
	1s
$end
$scope module id_tb $end
$var wire 5 ! Cad [4:0] $end
$var wire 3 " Shift_type [2:0] $end
$var wire 2 # PC_MUX_Select [1:0] $end
$var wire 1 $ I $end
$var wire 1 % GP_WE $end
$var wire 2 & GP_MUX_SEL [1:0] $end
$var wire 1 ' DM_WE $end
$var wire 4 ( Bf [3:0] $end
$var wire 4 ) Af [3:0] $end
$var wire 1 * ALU_MUX_SEL $end
$var reg 32 + instruction [31:0] $end
$scope module UUT $end
$var wire 1 * ALU_MUX_SEL $end
$var wire 5 , Cad [4:0] $end
$var wire 1 % GP_WE $end
$var wire 32 - Instruction [31:0] $end
$var wire 1 . alu $end
$var wire 5 / sa [4:0] $end
$var wire 5 0 rt [4:0] $end
$var wire 5 1 rs [4:0] $end
$var wire 5 2 rd [4:0] $end
$var wire 6 3 opc [5:0] $end
$var wire 1 4 j $end
$var wire 26 5 imm [25:0] $end
$var wire 26 6 iindex [25:0] $end
$var wire 6 7 fun [5:0] $end
$var wire 2 8 PC_MUX_Select [1:0] $end
$var wire 1 $ I $end
$var wire 2 9 GP_MUX_SEL [1:0] $end
$var wire 1 ' DM_WE $end
$var wire 4 : Bf [3:0] $end
$var wire 4 ; Af [3:0] $end
$var reg 3 < Shift_type [2:0] $end
$upscope $end
$upscope $end
$enddefinitions $end
#0
$dumpvars
bx <
b0 ;
b111 :
b10 9
b11 8
b100 7
b100001010000000000000100 6
b100 5
04
b100011 3
b0 2
b100 1
b101 0
b0 /
0.
b10001100100001010000000000000100 -
b0x0x ,
b10001100100001010000000000000100 +
0*
b0 )
b111 (
0'
b10 &
1%
1$
b11 #
bx "
b0x0x !
$end
#10
0%
b0 &
b0 9
1'
b101011 3
b10101100100001010000000000000100 +
b10101100100001010000000000000100 -
#20
1%
b10 )
b10 ;
1.
b1 (
b1 :
0'
b1000 3
b100000100001010000000000000100 +
b100000100001010000000000000100 -
#30
b11 (
b11 :
b1001 3
b100100100001010000000000000100 +
b100100100001010000000000000100 -
#40
b101 (
b101 :
b1010 3
b101000100001010000000000000100 +
b101000100001010000000000000100 -
#50
b111 (
b111 :
b1011 3
b101100100001010000000000000100 +
b101100100001010000000000000100 -
#60
b11 )
b11 ;
b1001 (
b1001 :
b1100 3
b110000100001010000000000000100 +
b110000100001010000000000000100 -
#70
b1011 (
b1011 :
b1101 3
b110100100001010000000000000100 +
b110100100001010000000000000100 -
#80
b1101 (
b1101 :
b1110 3
b111000100001010000000000000100 +
b111000100001010000000000000100 -
#90
b1111 (
b1111 :
b1111 3
b111100100001010000000000000100 +
b111100100001010000000000000100 -
#100
0%
b0 )
b0 ;
0.
b10 #
b10 8
b0 !
b0 ,
b1 3
b0 0
b100000000000000000000100 6
b10 (
b10 :
b100100000000000000000000100 +
b100100000000000000000000100 -
#110
b0x !
b0x ,
b1 0
b100000010000000000000100 6
b11 (
b11 :
b100100000010000000000000100 +
b100100000010000000000000100 -
#120
b1001 (
b1001 :
b100 3
b10000100000010000000000000100 +
b10000100000010000000000000100 -
#130
b1011 (
b1011 :
b101 3
b10100100000010000000000000100 +
b10100100000010000000000000100 -
#140
b0 !
b0 ,
b110 3
b0 0
b100000000000000000000100 6
b1100 (
b1100 :
b11000100000000000000000000100 +
b11000100000000000000000000100 -
#150
b1110 (
b1110 :
b111 3
b11100100000000000000000000100 +
b11100100000000000000000000100 -
#160
b1 "
b1 <
b11 #
b11 8
1*
0$
b0 3
b0 7
b101 0
b100 !
b100 ,
b100 2
b1 /
b10000001000000 5
b100001010010000001000000 6
b1 (
b1 :
b100001010010000001000000 +
b100001010010000001000000 -
#170
b10 "
b10 <
1%
b1 &
b1 9
b10 7
b10000001000010 5
b100001010010000001000010 6
b100001010010000001000010 +
b100001010010000001000010 -
#180
b11 "
b11 <
0%
b0 &
b0 9
b11 7
b10000001000011 5
b100001010010000001000011 6
b100001010010000001000011 +
b100001010010000001000011 -
#190
b100 "
b100 <
b100 7
b0 /
b10000000000100 5
b100001010010000000000100 6
b100001010010000000000100 +
b100001010010000000000100 -
#200
b101 "
b101 <
b110 7
b10000000000110 5
b100001010010000000000110 6
b100001010010000000000110 +
b100001010010000000000110 -
#210
b110 "
b110 <
b111 7
b10000000000111 5
b100001010010000000000111 6
b100001010010000000000111 +
b100001010010000000000111 -
#220
b0 "
b0 <
1%
1.
b100000 7
b10000000100000 5
b100001010010000000100000 6
b100001010010000000100000 +
b100001010010000000100000 -
#230
b1 )
b1 ;
b100001 7
b10000000100001 5
b100001010010000000100001 6
b100001010010000000100001 +
b100001010010000000100001 -
#240
b10 )
b10 ;
b100010 7
b10000000100010 5
b100001010010000000100010 6
b100001010010000000100010 +
b100001010010000000100010 -
#250
b11 )
b11 ;
b100011 7
b10000000100011 5
b100001010010000000100011 6
b100001010010000000100011 +
b100001010010000000100011 -
#260
b100 )
b100 ;
b100100 7
b10000000100100 5
b100001010010000000100100 6
b100001010010000000100100 +
b100001010010000000100100 -
#270
b101 )
b101 ;
b100101 7
b10000000100101 5
b100001010010000000100101 6
b100001010010000000100101 +
b100001010010000000100101 -
#280
b110 )
b110 ;
b100110 7
b10000000100110 5
b100001010010000000100110 6
b100001010010000000100110 +
b100001010010000000100110 -
#290
b111 )
b111 ;
b100111 7
b10000000100111 5
b100001010010000000100111 6
b100001010010000000100111 +
b100001010010000000100111 -
#300
b1010 )
b1010 ;
b101010 7
b10000000101010 5
b100001010010000000101010 6
b100001010010000000101010 +
b100001010010000000101010 -
#310
b1011 )
b1011 ;
b101011 7
b10000000101011 5
b100001010010000000101011 6
b100001010010000000101011 +
b100001010010000000101011 -
#320
0%
b0 )
b0 ;
0.
b1000 7
b10000000001000 5
b100001010010000000001000 6
b100001010010000000001000 +
b100001010010000000001000 -
#330
b1001 7
b10000000001001 5
b100001010010000000001001 6
b100001010010000000001001 +
b100001010010000000001001 -
#340
0*
b10 #
b10 8
1$
14
b10 3
b0 1
b0 0
b0 !
b0 ,
b0 2
b1001 5
b1001 6
b100 (
b100 :
b1000000000000000000000001001 +
b1000000000000000000000001001 -
#350
1%
b10 #
b10 8
b110 (
b110 :
bx !
bx ,
04
b11 3
b1100000000000000000000001001 +
b1100000000000000000000001001 -
