sem-2/ca-lab/week-6/hw/rom.v
module rom (
    input [2:0] address, 
    input sel,
    output reg [7:0] data
);

always @ (sel or address) begin
    if (~sel)
        data = 8'd00;
    else begin
        case (address)
            0: data = 8'd01;
            1: data = 8'd02;
            2: data = 8'd03;
            3: data = 8'd04;
            4: data = 8'd60;
            5: data = 8'd42;
            6: data = 8'd37;
            7: data = 8'd22;
        endcase
    end
end

endmodule

sem-2/ca-lab/week-6/hw/rom_tb.v
`include "rom.v"

module rom_tb();

reg [2:0] addr;
reg sel;
wire [7:0] data;

rom UUT(.address(addr), .sel(sel), .data(data));

initial begin
    $dumpfile("rom_tb.vcd");
    $dumpvars(0, rom_tb);
    addr = 0;
    sel = 0;
    #5; sel = 1;
    #5; addr = 1;
    #5; addr = 2;
    #5; addr = 3;
    #5; addr = 4;
    #5; sel = 0;
    #5; sel = 1;
    #5; addr = 5;
    #5; addr = 6;
    #5; addr = 7;
    #5;
    $finish;
end

endmodule

sem-2/ca-lab/week-6/hw/rom_tb.vcd
$date
	Fri Apr 14 22:25:06 2023
$end
$version
	Icarus Verilog
$end
$timescale
	1s
$end
$scope module rom_tb $end
$var wire 8 ! data [7:0] $end
$var reg 3 " addr [2:0] $end
$var reg 1 # sel $end
$scope module UUT $end
$var wire 3 $ address [2:0] $end
$var wire 1 # sel $end
$var reg 8 % data [7:0] $end
$upscope $end
$upscope $end
$enddefinitions $end
#0
$dumpvars
b0 %
b0 $
0#
b0 "
b0 !
$end
#5
b1 !
b1 %
1#
#10
b10 !
b10 %
b1 "
b1 $
#15
b11 !
b11 %
b10 "
b10 $
#20
b100 !
b100 %
b11 "
b11 $
#25
b111100 !
b111100 %
b100 "
b100 $
#30
b0 !
b0 %
0#
#35
b111100 !
b111100 %
1#
#40
b101010 !
b101010 %
b101 "
b101 $
#45
b100101 !
b100101 %
b110 "
b110 $
#50
b10110 !
b10110 %
b111 "
b111 $
