sem-2/ca-lab/week-9/lab/alu.v
module ALU (
    input i,
    input [31:0] SrcA, SrcB,
    input [3:0] af,
    output reg [31:0] Alures,
    output Zero, Neg, ovfalu
);
    always @(af or i or SrcA or SrcB) begin
        case (af)
            4'b0000 : Alures = SrcA + SrcB ;
            4'b0001 : Alures = SrcA + SrcB ;
            4'b0010 : Alures = SrcA - SrcB ;
            4'b0011 : Alures = SrcA - SrcB ;
            4'b0100 : Alures = SrcA & SrcB ;
            4'b0101 : Alures = SrcA | SrcB ;
            4'b0110 : Alures = SrcA ^ SrcB ;
            4'b0111 : Alures = i ? SrcB << 16 : SrcA ~| SrcB;
            4'b1010 : Alures = (SrcA[31] ^ SrcB[31]) ? SrcA[30:0] < SrcB[30:0] : SrcA[31] ;
            4'b1011 : Alures = SrcA < SrcB ;
        endcase
    end
    assign Zero = Alures == 0;
    assign Neg = (af < 4) & Alures[31];
    assign ovfalu = (af == 0 | af == 2) & (Alures[31] ? (SrcA[31] & SrcB[31]) : (SrcA[31] | SrcB[31]));
endmodule

sem-2/ca-lab/week-9/lab/alu-tb.v
module alu_tb();

	reg i;
	reg [31:0] SrcA;
	reg [31:0] SrcB;
	reg [3:0] af;
	wire [31:0] Alures;
	wire Zero;
	wire Neg;
	wire ovfalu;

	ALU UUT (
		.i(i),
		.SrcA(SrcA),
		.SrcB(SrcB),
		.af(af),
		.Alures(Alures),
		.Zero(Zero),
		.Neg(Neg),
		.ovfalu(ovfalu)
	);

	initial begin
		$dumpfile("alu-tb.vcd"); 
		$dumpvars(0, alu_tb);
		SrcA = 32'd3;
		SrcB = 32'd4;
		i = 1;
		af = 4'b0000;
		#10;
		af = 4'b0001;
		#10;
		af = 4'b0010;
		#10;
		af = 4'b0011;
		#10;
		af = 4'b0100;
		#10;
		af = 4'b0101;
		#10;
		af = 4'b0110;
		#10;
		af = 4'b0111;
		#10;
		af = 4'b1010;
		#10;
		af = 4'b1011;
		#10;
		i = 0;
		af = 4'b0000;
		#10;
		af = 4'b0001;
		#10;
		af = 4'b0010;
		#10;
		af = 4'b0011;
		#10;
		af = 4'b0100;
		#10;
		af = 4'b0101;
		#10;
		af = 4'b0110;
		#10;
		af = 4'b0111;
		#10;
		af = 4'b1010;
		#10;
		af = 4'b1011;
		#10;     
	end
endmodule

sem-2/ca-lab/week-10/lab/alu-tb.vcd
$date
	Fri May 26 19:17:31 2023
$end
$version
	Icarus Verilog
$end
$timescale
	1s
$end
$scope module alu_tb $end
$var wire 1 ! ovfalu $end
$var wire 1 " Zero $end
$var wire 1 # Neg $end
$var wire 32 $ Alures [31:0] $end
$var reg 32 % SrcA [31:0] $end
$var reg 32 & SrcB [31:0] $end
$var reg 4 ' af [3:0] $end
$var reg 1 ( i $end
$scope module UUT $end
$var wire 1 # Neg $end
$var wire 32 ) SrcA [31:0] $end
$var wire 32 * SrcB [31:0] $end
$var wire 4 + af [3:0] $end
$var wire 1 ( i $end
$var wire 1 ! ovfalu $end
$var wire 1 " Zero $end
$var reg 32 , Alures [31:0] $end
$upscope $end
$upscope $end
$enddefinitions $end
#0
$dumpvars
b111 ,
b0 +
b100 *
b11 )
1(
b0 '
b100 &
b11 %
b111 $
0#
0"
0!
$end
#10
b1 '
b1 +
#20
1#
b11111111111111111111111111111111 $
b11111111111111111111111111111111 ,
b10 '
b10 +
#30
b11 '
b11 +
#40
1"
b0 $
b0 ,
0#
b100 '
b100 +
#50
0"
b111 $
b111 ,
b101 '
b101 +
#60
b110 '
b110 +
#70
b1000000000000000000 $
b1000000000000000000 ,
b111 '
b111 +
#80
b1 $
b1 ,
b1010 '
b1010 +
#90
b1011 '
b1011 +
#100
b111 $
b111 ,
b0 '
b0 +
0(
#110
b1 '
b1 +
#120
1#
b11111111111111111111111111111111 $
b11111111111111111111111111111111 ,
b10 '
b10 +
#130
b11 '
b11 +
#140
1"
b0 $
b0 ,
0#
b100 '
b100 +
#150
0"
b111 $
b111 ,
b101 '
b101 +
#160
b110 '
b110 +
#170
b11111111111111111111111111111000 $
b11111111111111111111111111111000 ,
b111 '
b111 +
#180
b1 $
b1 ,
b1010 '
b1010 +
#190
b1011 '
b1011 +
