sem-2/ca-lab/week-10/lab/pc.v
module PC_module (
    input Clock, Reset, S,
    input [31:0] Next_PC, data_addr_in, data_in,
    output [31:0] PC_out, 
    output reg [31:0] Iout, Mout,
    output reg E
);
    reg [31:0] pc;
    reg [31:0] I;
    reg [31:0] memory [0:255];

    integer i;
    initial begin
        for (i = 0; i < 32; i = i + 1) memory[1] = 32'h0;
    end

    always @(posedge Reset or posedge Clock) begin
        if (Reset) begin
            E = 0;
            pc = 0;
        end else if (!E) begin
            E = 1;
            pc = Next_PC;
            I = memory[pc >> 2];
            Mout = I;
        end else begin
            E = 0;
            if (S) begin
                memory[data_addr_in >> 2] = data_in;
            end else begin
                Mout = memory[data_addr_in >> 2];
            end
            Iout = I;
        end
    end

    assign PC_out = pc;

endmodule

sem-2/ca-lab/week-10/lab/pc-tb.v
module pc_tb();
	reg Clock;
	reg Reset;
	reg S;
	reg [31:0] Next_PC, data_addr_in, data_in;
	wire E;
	wire [31:0] PC_out, Iout, Mout;

	PC_module UUT (
		.Clock(Clock),
		.Reset(Reset),
		.S(S),
		.Next_PC(Next_PC),
		.data_addr_in(data_addr_in),
		.data_in(data_in),
		.E(E),
		.PC_out(PC_out),
		.Iout(Iout),
		.Mout(Mout)
	);

	always #5 Clock = ~Clock;

	initial begin
		$dumpfile("pc-tb.vcd"); 
		$dumpvars(0, pc_tb);
		Clock = 0;
		Reset = 1;
		S = 0;
		Next_PC = 32'h0;
		data_addr_in = 32'h0;
		data_in = 32'h0;

		#10;
		Reset = 0;

		#10;
		Next_PC = 32'h4;
		S = 1;
		data_addr_in = 32'h8;
		data_in = 32'h12345678;

		#30; 
		Next_PC = 32'h8; 
		S = 0; 
		data_addr_in = 32'h8;
		data_in = 32'h9abcdef0;

		#10; 
		$finish;
	end
endmodule

sem-2/ca-lab/week-10/lab/pc-tb.vcd
$date
	Fri Jun  2 23:57:46 2023
$end
$version
	Icarus Verilog
$end
$timescale
	1s
$end
$scope module pc_tb $end
$var wire 32 ! PC_out [31:0] $end
$var wire 32 " Mout [31:0] $end
$var wire 32 # Iout [31:0] $end
$var wire 1 $ E $end
$var reg 1 % Clock $end
$var reg 32 & Next_PC [31:0] $end
$var reg 1 ' Reset $end
$var reg 1 ( S $end
$var reg 32 ) data_addr_in [31:0] $end
$var reg 32 * data_in [31:0] $end
$scope module UUT $end
$var wire 1 % Clock $end
$var wire 32 + Next_PC [31:0] $end
$var wire 32 , PC_out [31:0] $end
$var wire 1 ' Reset $end
$var wire 1 ( S $end
$var wire 32 - data_addr_in [31:0] $end
$var wire 32 . data_in [31:0] $end
$var reg 1 $ E $end
$var reg 32 / I [31:0] $end
$var reg 32 0 Iout [31:0] $end
$var reg 32 1 Mout [31:0] $end
$var reg 32 2 pc [31:0] $end
$var integer 32 3 i [31:0] $end
$upscope $end
$upscope $end
$enddefinitions $end
#0
$dumpvars
b100000 3
b0 2
bx 1
bx 0
bx /
b0 .
b0 -
b0 ,
b0 +
b0 *
b0 )
0(
1'
b0 &
0%
0$
bx #
bx "
b0 !
$end
#5
1%
#10
0%
0'
#15
1$
1%
#20
0%
b10010001101000101011001111000 *
b10010001101000101011001111000 .
b1000 )
b1000 -
1(
b100 &
b100 +
#25
0$
1%
#30
0%
#35
b0 "
b0 1
b0 /
b100 !
b100 ,
b100 2
1$
1%
#40
0%
#45
b0 #
b0 0
0$
1%
#50
0%
b10011010101111001101111011110000 *
b10011010101111001101111011110000 .
0(
b1000 &
b1000 +
#55
b10010001101000101011001111000 "
b10010001101000101011001111000 1
b10010001101000101011001111000 /
b1000 !
b1000 ,
b1000 2
1$
1%
