sem-2/ca-lab/week-3/lab/full_adder.v
module full_adder (
    A,
    B,
    C_in,
    S,
    C_out
);
    input A;
    input B;
    input C_in;

    output S;
    output C_out;

    wire D;
    wire E;
    wire F;

    // Sum
    assign S = A ^ B ^ C_in;
    
    // Carry
    assign D = B & C_in;
    assign E = A & B;
    assign F = A & C_in;
    assign C_out = D | E | F;

endmodule

//   A  B C_in | S C_out
//   0  0  0   | 0   0
//   0  0  1   | 1   0
//   0  1  0   | 1   0
//   0  1  1   | 0   1
//   1  0  0   | 1   0
//   1  0  1   | 0   1
//   1  1  0   | 0   1
//   1  1  1   | 1   1

// DNF
// S = (~A & ~B & C_in) | (~A & B & ~C_in) | (A & ~B & ~C_in) | (A & B & C_in)
//   = (~A & (~B & C_in | B & ~C_in)) | (A & (~B & ~C_in | B & C_in))
//   = (~A & (B ^ C_in)) | (A & ~(B ^ C_in))
//   = A ^ (B ^ C_in) 
//   = A ^ B ^ C_in

// C_out = (~A & B & C_in) | (A & ~B & C_in) | (A & B & ~C_in) | (A & B & C_in) 
//       = (A & (~B & C_in | B & ~C_in | B & C_in)) | (~A & B & C_in)
//       = (A & (B | C_in)) | (~A & (B & C_in))
//       = (B & C_in) | (A & (B | C_in))
//       = (B & C_in) | (A & B) | (A & C_in)

sem-2/ca-lab/week-3/lab/full_adder_tb.v
`timescale 1ns / 1ns

`include "full_adder.v"

module full_adder_tb;

    reg A;
    reg B;
    reg C_in;
    wire S;
    wire C_out;

    full_adder full_adder_inst
    (
        A,
        B,
        C_in,
        S,
        C_out
    );

    initial begin
        $dumpfile("full_adder_tb.vcd");
        $dumpvars(0,full_adder_tb);

        A = 0;
        B = 0;
        C_in = 0;
        #10;
        A = 0;
        B = 1;
        C_in = 0;
        #10;
        A = 1;
        B = 0;
        C_in = 0;
        #10;
        A = 1;
        B = 1;
        C_in = 0;
        #10;
        A = 0;
        B = 0;
        C_in = 1;
        #10;
        A = 0;
        B = 1;
        C_in = 1;
        #10;
        A = 1;
        B = 0;
        C_in = 1;
        #10;
        A = 1;
        B = 1;
        C_in = 1;
        #10;

        $display("test complete");
    end 

endmodule

sem-2/ca-lab/week-3/lab/full_adder_tb.vcd
$date
	Fri Mar 24 23:45:16 2023
$end
$version
	Icarus Verilog
$end
$timescale
	1ns
$end
$scope module full_adder_tb $end
$var wire 1 ! S $end
$var wire 1 " C_out $end
$var reg 1 # A $end
$var reg 1 $ B $end
$var reg 1 % C_in $end
$scope module full_adder_inst $end
$var wire 1 # A $end
$var wire 1 $ B $end
$var wire 1 % C_in $end
$var wire 1 " C_out $end
$var wire 1 & D $end
$var wire 1 ' E $end
$var wire 1 ( F $end
$var wire 1 ! S $end
$upscope $end
$upscope $end
$enddefinitions $end
#0
$dumpvars
0(
0'
0&
0%
0$
0#
0"
0!
$end
#10
1!
1$
#20
0$
1#
#30
1"
0!
1'
1$
#40
0"
1!
0'
1%
0$
0#
#50
1"
0!
1&
1$
#60
0&
1(
0$
1#
#70
1!
1&
1'
1$
