sem-2/ca-lab/week-5/hw/register.v
module register (
    input reset,
    input load,
    input set,
    input [2:0] data,
    output reg [2:0] out = 0
);

always @(posedge load) begin
    out = data;
end

always @(posedge set) begin
    out = 3'b111;
end

always @(posedge reset) begin
    out = 3'b000;
end

endmodule

sem-2/ca-lab/week-5/hw/register-tb.v
`include "register.v"

module register_tb();

reg clock;
reg reset;
reg load;
reg set;
reg [2:0] data;
wire [2:0] out;

register UUT(.reset(reset), .load(load), .set(set), .data(data), .out(out));

initial begin
    $dumpfile("register_tb.vcd");
    $dumpvars(0, register_tb);
    load = 0;
    reset = 0;
    set = 0;
    data = 3'b010;
    #10;
    load = 1;
    #10;
    load = 0;
    #10;
    reset = 1;
    #10;
    reset = 0;
    #10;
    set = 1;
    #10;
    set = 0;
    #10;
    data = 3'b110;
    #4;
    load = 1;
    #4;
    load = 0;
    #4;
    load = 1;
    #4;
    load = 0;
    #40; $finish;
end

endmodule

sem-2/ca-lab/week-5/hw/register_tb.vcd
$date
	Fri Apr  7 23:28:52 2023
$end
$version
	Icarus Verilog
$end
$timescale
	1s
$end
$scope module register_tb $end
$var wire 3 ! out [2:0] $end
$var reg 3 " data [2:0] $end
$var reg 1 # load $end
$var reg 1 $ reset $end
$var reg 1 % set $end
$scope module UUT $end
$var wire 3 & data [2:0] $end
$var wire 1 # load $end
$var wire 1 $ reset $end
$var wire 1 % set $end
$var reg 3 ' out [2:0] $end
$upscope $end
$upscope $end
$enddefinitions $end
#0
$dumpvars
b0 '
b10 &
0%
0$
0#
b10 "
b0 !
$end
#10
b10 !
b10 '
1#
#20
0#
#30
b0 !
b0 '
1$
#40
0$
#50
b111 !
b111 '
1%
#60
0%
#70
b110 "
b110 &
#74
b110 !
b110 '
1#
#78
0#
#82
1#
#86
0#
