sem-2/ca-lab/week-3/hw/triple_impl.v
module tripple_impl (
    A,
    B,
    C,
    X
);
    input A;
    input B;
    input C;
    output X;

    wire D;
    wire E;
    assign D = A & B;
    assign E = ~D;
    
    assign X = E | C;

endmodule

sem-2/ca-lab/week-3/hw/triple_impl_tb.v
`timescale 1ns / 1ns

`include "triple_impl.v"

module triple_imple_tb;

    reg A;
    reg B;
    reg C;
    wire X;

    tripple_impl tripple_impl_inst
    (
        A,
        B,
        C,
        X
    );

    initial begin
        $dumpfile("triple_imple_tb.vcd");
        $dumpvars(0,triple_imple_tb);

        A = 0;
        B = 0;
        C = 0;
        #10;
        A = 0;
        B = 1;
        C = 0;
        #10;
        A = 1;
        B = 0;
        C = 0;
        #10;
        A = 1;
        B = 1;
        C = 0;
        #10;
        A = 0;
        B = 0;
        C = 1;
        #10;
        A = 0;
        B = 1;
        C = 1;
        #10;
        A = 1;
        B = 0;
        C = 1;
        #10;
        A = 1;
        B = 1;
        C = 1;
        #10;

        $display("test complete");
    end 

endmodule

sem-2/ca-lab/week-3/hw/triple_imple_tb.vcd
$date
	Fri Mar 31 22:19:27 2023
$end
$version
	Icarus Verilog
$end
$timescale
	1ns
$end
$scope module triple_imple_tb $end
$var wire 1 ! X $end
$var reg 1 " A $end
$var reg 1 # B $end
$var reg 1 $ C $end
$scope module tripple_impl_inst $end
$var wire 1 " A $end
$var wire 1 # B $end
$var wire 1 $ C $end
$var wire 1 % D $end
$var wire 1 & E $end
$var wire 1 ! X $end
$upscope $end
$upscope $end
$enddefinitions $end
#0
$dumpvars
1&
0%
0$
0#
0"
1!
$end
#10
1#
#20
0#
1"
#30
0!
0&
1%
1#
#40
1&
1!
0%
1$
0#
0"
#50
1#
#60
0#
1"
#70
0&
1%
1#
